{
	"id":"android0007",
	"name":"Android经典项目案例开发实战宝典 郭金尚 电子通信 计算机开发 新华书店正版畅销图书籍",
	"src":"assets/index/android/android0007.jpg",
	"price":62,
	"post":0.00,
	"sail":421,
	"comment":26,
	"stock":142,
	"relate":[
					{
						"src":"assets/index/android/android0001.jpg",
						"name":"Android基础教程(第4版)",
						"price":37,
						"id":"android0001"
					},{
						"src":"assets/index/android/android0003.jpg",
						"name":"Android经典项目开发实战",
						"price":67,
						"id":"android0003"
					},{
						"src":"assets/index/android/android0004.jpg",
						"name":"深入理解Android 5.0系统",
						"price":81,
						"id":"android0004"
					},{
						"src":"assets/index/android/android0005.jpg",
						"name":"Android开发实战经典",
						"price":47,
						"id":"android0005"
					},{
						"src":"assets/index/android/android0006.jpg",
						"name":"第一行代码-Android",
						"price":52,
						"id":"android0006"
					},{
						"src":"assets/index/android/android0002.jpg",
						"name":"Android 从入门到精通",
						"price":87,
						"id":"android0002"
					},{
						"src":"assets/index/android/android0008.jpg",
						"name":"疯狂Android讲义",
						"price":72,
						"id":"android0008"
					}
			],
	"basic":{
				"title":"ANDROID经典项目案例开发实",
				"packag":"否",
				"name":"Android经典项目案例开发实战宝典",
				"price":"89.00元",
				"press":"清华大学出版社",
				"press_time":"2013年9月",
				"author":"郭金尚",
				"block":"中国大陆",
				"format":"16开"
				},
	"book_info":" 郭金尚，毕业于华中科技大学。从事移动开发多年，对Android系统有颇为深入的研究。在平板电脑开发、Amlogic平台和VIA平台等领域有**深厚的积累。主要负责Android应用程序的开发和架构设计，积累了大量的实战经验。开发过多个系统应用和上线应用。此外还对Android Framework有深入研究，能根据平台特性对Android系统进行垂直定制。<br/>",
	"catalog":"第1篇 Android起步技术<br/><br/>第1章 搭建Android开发环境(教学视频：18分钟)<br/><br/>1.1 Android的诞生<br/><br/>1.1.1 Android的发展史<br/><br/>1.1.2 Android的发行版本<br/><br/>1.2 Android的系统架构及特性<br/><br/>1.2.1 Android的系统架构<br/><br/>1.2.2 Android的特性<br/><br/>1.3 Android的开发环境的搭建<br/><br/>1.4 Android调试<br/><br/>1.5 其他工具的使用<br/><br/>1.6 本章小结<br/><br/>第2章 Android程序开发基础(教学视频：31分钟)<br/><br/>第2篇 Android典型应用实战案例<br/><br/>第3章 计算器(教学视频：38分钟)<br/><br/>第4章 电子词典(教学视频：18分钟)<br/><br/>第5章 文件管理器(教学视频：51分钟)<br/><br/>第6章 备忘录(教学视频：37分钟)<br/><br/>第7章 短信收发工具(教学视频：19分钟)<br/><br/>第8章 通讯录(教学视频：29分钟)<br/><br/>第9章 任务管理器(教学视频：29分钟)<br/><br/>第10章 软件管理器(教学视频：19分钟)<br/><br/>第3篇 Android网络应用实战案例<br/><br/>第11章 Android公交查询(教学视频：44分钟)<br/><br/>第12章 股票查询软件(教学视频：32分钟)<br/><br/>第13章 Google天气客户端(教学视频：16分钟)<br/><br/>第14章 RSS新闻阅读器(教学视频：35分钟)<br/><br/>第15章 Android地图应用(教学视频：14分钟)<br/><br/>第16章 新浪微博客户端(教学视频：52分钟)<br/><br/>第4篇 Android影音应用实战案例<br/><br/>第17章 MP3播放器(教学视频：55分钟)<br/><br/>第18章 Android照相机(教学视频：13分钟)<br/><br/>第19章 视频播放器(教学视频：29分钟)<br/><br/>第5篇 Android游戏开发实战案例<br/><br/>第20章 小兔跳铃铛(教学视频：35分钟)<br/><br/>第21章 飞行射击游戏(教学视频：21分钟)<br/><br/>第22章 3D迷宫游戏(教学视频：33分钟)<br/><br/>",
	"rate":"93%",
	"assess":[
				{
					"user":"aaaaa",
					"time":"2015-06-28 17:34:43",
					"content":"与我之前看到的评价不同，我收到的这书简直包装完美，印刷完美，纸质完美。而且内容丰富，讲的特别详细。绝对值这个价"
				},{
					"user":"bbbbb",
					"time":"2015-06-28 17:34:43",
					"content":"很棒的一本书！之前看了评论有点不敢买还特地去了新华书店，但是新华书店的也是没有塑封而且还破，关键还128。这本书的顺序和我现在用的两本教材都不一样，感觉这样的排版又新鲜又有乐趣，好评"
				},{
					"user":"ccccc",
					"time":"2015-06-28 17:34:43",
					"content":"很好，正版，很有分量，当然就像其他人说的，包装不会很仔细，不过书籍也没事，我买了三本就是放在一个纸箱里的，运来也还好，没有损坏 服务很好"
				},{
					"user":"ddddd",
					"time":"2015-06-28 17:34:43",
					"content":"书看起来像正版的，质量很好，包装也很好，物流给力，夜里拍的，夜里就发货了，第二天就到了，好评，下次买书就在这家买了"
				},{
					"user":"eeeee",
					"time":"2015-06-28 17:34:43",
					"content":"书很好，印刷很清晰，看着挺舒服的?好评"
				},{
					"user":"fffff",
					"time":"2015-06-28 17:34:43",
					"content":"书挺好的，包装就一层塑料纸，还好没破。物流很快，第二天就到了"
				},{
					"user":"ggggg",
					"time":"2015-06-28 17:34:43",
					"content":"好书，是正品，送货挺快的，不得不给一个五星好评。"
				},{
					"user":"hhhhh",
					"time":"2015-06-28 17:34:43",
					"content":"很好很好很好 很好很好很好 很好很好很好，是正品，就是书的外封皮有些破损，但完全不影响使用"
				},{
					"user":"iiiii",
					"time":"2015-06-28 17:34:43",
					"content":"物流很给力。转天就送到了。书没破损。内容我看不懂。但是我弟弟说挺好的。所以给的五星。"
				},{
					"user":"jjjjj",
					"time":"2015-06-28 17:34:43",
					"content":"字迹清晰，很好，纸张结实，讲的也是详细，例子还可以"
				},{
					"user":"kkkkk",
					"time":"2015-06-28 17:34:43",
					"content":"当当的物流一如既往的好！！赞！！！！！！！书也很不错，就是书的包装显得扣，不说了，学习去了！"
				},{
					"user":"lllll",
					"time":"2015-06-28 17:34:43",
					"content":"相当不错，绝对正版，很厚，肯定对学习特别有帮助，赞"
				},{
					"user":"mmmmm",
					"time":"2015-06-28 17:34:43",
					"content":"发票拖了半月才发，这效率还是别来坑人"
				},{
					"user":"nnnnn",
					"time":"2015-06-28 17:34:43",
					"content":"书没有损坏，其实也没有评论里说的那么严重，快递本来想给4星，但最后看快递员是个老大爷，心一酸，觉得谁都不容易啊，给5星"
				},{
					"user":"ooooo",
					"time":"2015-06-28 17:34:43",
					"content":"快递很快，隔天就到了，但是书右上角有折痕，而且不止一页。包装太简陋了，亲爱的店主你这是走贵书高冷风格吗，人靠衣装，书靠包装。虽说书的内容很精华，但是书这么厚不包装很容易折到。你让我这个强迫症情何以堪。"
				},{
					"user":"ppppp",
					"time":"2015-06-28 17:34:43",
					"content":"货收到了，快递很快，虽然包装不太好，书有划痕，但是里面是好的，没完美强迫症，可以看，是正版，纸张很好，想学知识的就别在意那么多不重要的细节了。好评。"
				},{
					"user":"qqqqq",
					"time":"2015-06-28 17:34:43",
					"content":"包装太寒酸了，不过还好书没有任何损伤，斥巨资买的书我要刷一波c"
				},{
					"user":"rrrrr",
					"time":"2015-06-28 17:34:43",
					"content":"为什么不用纸皮包一下，我拿到时你们的塑料袋包装都破了"
				},{
					"user":"sssss",
					"time":"2015-06-28 17:34:43",
					"content":"正版书，就是包装太一般了，封面上有印子"
				},{
					"user":"ttttt",
					"time":"2015-06-28 17:34:43",
					"content":"就包了一个袋………完全不知道爱护书籍，这个好评我是刷我的评价的"
				},{
					"user":"uuuuu",
					"time":"2015-06-28 17:34:43",
					"content":"包装真心破，像我这种经常在书上画娃娃的人都看不下去了，就一个快递袋，里面装了一本书，关键是快递袋还破了，其实你把包装搞好一点，加价5块钱我都可以接收。。。"
				},{
					"user":"vvvvv",
					"time":"2015-06-28 17:34:43",
					"content":"相当快啊，就是跑好远去取的。纸张特别好，很重。超值的。"
				},{
					"user":"wwwww",
					"time":"2015-06-28 17:34:43",
					"content":"发货很快，晚上11点多下的单，第二天上午就到了，目测是正版的，从纸张、印刷质量来看都还行"
				},{
					"user":"xxxxx",
					"time":"2015-06-28 17:34:43",
					"content":"速度很快，昨天晚上订的今天中午就到了，只可惜书并不是塑胶封的，磨损比较严重"
				},{
					"user":"yyyyy",
					"time":"2015-06-28 17:34:43",
					"content":"是很好，就是被压了。书边有折痕，对于有强迫症的我来说心里不好受，"
				},{
					"user":"zzzzz",
					"time":"2015-06-28 17:34:43",
					"content":"正在看，书的质量还不错，就是太难了，慢慢学哈哈"
				}
			]
}
