[
	{
		"type":"C语言",
		"list":[
					{
						"src":"assets/index/c/c0001.jpg",
						"name":"C Primer Plus（第五版）",
						"price":40.1,
						"id":"c0001"
					},{
						"src":"assets/index/c/c0002.jpg",
						"name":"C 程序设计语言（第2版）",
						"price":21,
						"id":"c0002"
					},{
						"src":"assets/index/c/c0003.jpg",
						"name":"C陷阱与缺陷",
						"price":24,
						"id":"c0003"
					},{
						"src":"assets/index/c/c0004.jpg",
						"name":"数据结构与算法分析（C语言描述）",
						"price":23,
						"id":"c0004"
					},{
						"src":"assets/index/c/c0005.jpg",
						"name":"C和指针",
						"price":44,
						"id":"c0005"
					},{
						"src":"assets/index/c/c0006.jpg",
						"name":"数据结构（C语言版）",
						"price":35,
						"id":"c0006"
					},{
						"src":"assets/index/c/c0007.jpg",
						"name":"C语言入门经典",
						"price":36,
						"id":"c0007"
					},{
						"src":"assets/index/c/c0008.jpg",
						"name":"C语言从入门到精通",
						"price":33,
						"id":"c0008"
					}]
	},{
		"type":"C++语言",
		"list":[
					{
						"src":"assets/index/c++/c++0001.jpg",
						"name":"C++ Primer(第五版)",
						"price":88,
						"id":"c++0001"
					},{
						"src":"assets/index/c++/c++0002.jpg",
						"name":"Visual C++从入门到精通",
						"price":44,
						"id":"c++0002"
					},{
						"src":"assets/index/c++/c++0003.jpg",
						"name":"C++语言程序设计（特别版）",
						"price":88,
						"id":"c++0003"
					},{
						"src":"assets/index/c++/c++0004.jpg",
						"name":"21天学通C++",
						"price":37,
						"id":"c++0004"
					},{
						"src":"assets/index/c++/c++0005.jpg",
						"name":"C++入门经典（第4版）",
						"price":55,
						"id":"c++0005"
					},{
						"src":"assets/index/c++/c++0006.jpg",
						"name":"C++ Primer(第五版)习题集",
						"price":23,
						"id":"c++0006"
					},{
						"src":"assets/index/c++/c++0007.jpg",
						"name":"C++ Primer Plus(第六版)",
						"price":59,
						"id":"c++0007"
					},{
						"src":"assets/index/c++/c++0008.jpg",
						"name":"C++ 编程思想（两卷合订本）",
						"price":87,
						"id":"c++0008"
					}]
	},{
		"type":"Java语言",
		"list":[
					{
						"src":"assets/index/java/java0001.jpg",
						"name":"数据结构与算法分析（Java语言描述）",
						"price":54,
						"id":"java0001"
					},{
						"src":"assets/index/java/java0002.jpg",
						"name":"Java从入门到精通（第3版）",
						"price":87,
						"id":"java0002"
					},{
						"src":"assets/index/java/java0003.jpg",
						"name":"Java入门经典（第7版）",
						"price":87,
						"id":"java0003"
					},{
						"src":"assets/index/java/java0004.jpg",
						"name":"Head first Java（中文版）",
						"price":47,
						"id":"java0004"
					},{
						"src":"assets/index/java/java0005.jpg",
						"name":"Java核心技术（卷1）",
						"price":87,
						"id":"java0005"
					},{
						"src":"assets/index/java/java0006.jpg",
						"name":"Java核心技术（卷2）",
						"price":94,
						"id":"java0006"
					},{
						"src":"assets/index/java/java0007.jpg",
						"name":"Java编程思想（第4版）",
						"price":72,
						"id":"java0007"
					},{
						"src":"assets/index/java/java0008.jpg",
						"name":"疯狂java讲义（第3版）",
						"price":76,
						"id":"java0008"
					}]
	},{
		"type":"Android",
		"list":[
					{
						"src":"assets/index/android/android0001.jpg",
						"name":"Android 基础教程（第4版）",
						"price":37,
						"id":"android0001"
					},{
						"src":"assets/index/android/android0002.jpg",
						"name":"Android从入门到精通",
						"price":87,
						"id":"android0002"
					},{
						"src":"assets/index/android/android0003.jpg",
						"name":"Android经典项目开发实战",
						"price":67,
						"id":"android0003"
					},{
						"src":"assets/index/android/android0004.jpg",
						"name":"深入解析Android 5.0系统",
						"price":81,
						"id":"android0004"
					},{
						"src":"assets/index/android/android0005.jpg",
						"name":"Android开发实战经典",
						"price":47,
						"id":"android0005"
					},{
						"src":"assets/index/android/android0006.jpg",
						"name":"第一行代码-Android",
						"price":52,
						"id":"android0006"
					},{
						"src":"assets/index/android/android0007.jpg",
						"name":"Android经典项目案例开发",
						"price":62,
						"id":"android0007"
					},{
						"src":"assets/index/android/android0008.jpg",
						"name":"疯狂Android讲义",
						"price":72,
						"id":"android0008"
					}]
	},{
		"type":"iOS",
		"list":[
					{
						"src":"assets/index/ios/ios0001.jpg",
						"name":"疯狂iOS讲义（上）",
						"price":64,
						"id":"ios0001"
					},{
						"src":"assets/index/ios/ios0002.jpg",
						"name":"疯狂iOS讲义（下）",
						"price":65,
						"id":"ios0002"
					},{
						"src":"assets/index/ios/ios0003.jpg",
						"name":"iOS开发指南（第3版）",
						"price":67,
						"id":"ios0003"
					},{
						"src":"assets/index/ios/ios0004.jpg",
						"name":"iOS 9开发快速入门",
						"price":49,
						"id":"ios0004"
					},{
						"src":"assets/index/ios/ios0005.jpg",
						"name":"iOS开发范例实战宝典（基础篇）",
						"price":77,
						"id":"ios0005"
					},{
						"src":"assets/index/ios/ios0006.jpg",
						"name":"iOS开发进阶",
						"price":55,
						"id":"ios0006"
					},{
						"src":"assets/index/ios/ios0007.jpg",
						"name":"iOS 9 开发指南",
						"price":63,
						"id":"ios0007"
					},{
						"src":"assets/index/ios/ios0008.jpg",
						"name":"Swift与Cocoa框架开发",
						"price":62.3,
						"id":"ios0008"
					}]
	},{
		"type":"Web",
		"list":[
					{
						"src":"assets/index/web/web0001.jpg",
						"name":"Javascript权威指南",
						"price":88.8,
						"id":"web0001"
					},{
						"src":"assets/index/web/web0002.jpg",
						"name":"Javascript高级程序设计（第3版）",
						"price":71.5,
						"id":"web0002"
					},{
						"src":"assets/index/web/web0003.jpg",
						"name":"Javascript语言精粹（修订版）",
						"price":36.7,
						"id":"web0003"
					},{
						"src":"assets/index/web/web0004.jpg",
						"name":"HTML5权威指南",
						"price":87,
						"id":"web0004"
					},{
						"src":"assets/index/web/web0005.jpg",
						"name":"HTML5与CSS3基础教程",
						"price":44,
						"id":"web0005"
					},{
						"src":"assets/index/web/web0006.jpg",
						"name":"图解CSS3（核心技术与案例实战）",
						"price":65.2,
						"id":"web0006"
					},{
						"src":"assets/index/web/web0007.jpg",
						"name":"HTML5与CSS3权威指南（第3版）",
						"price":55.2,
						"id":"web0007"
					},{
						"src":"assets/index/web/web0008.jpg",
						"name":"你不知道的Javascript",
						"price":41.7,
						"id":"web0008"
					}]
		}]